Main/__init__.py
PassWord_Genm-0.1.dist-info/LICENCE.TXT
PassWord_Genm-0.1.dist-info/METADATA
PassWord_Genm-0.1.dist-info/WHEEL
PassWord_Genm-0.1.dist-info/top_level.txt
PassWord_Genm-0.1.dist-info/RECORD
