Metadata-Version: 2.1
Name: PassWord-Genm
Version: 0.1
Summary: This is a test
Home-page: UNKNOWN
Author: 5nz
Author-email: mdasmfasmmfam@gmail.com
License: UNKNOWN
Platform: UNKNOWN
Classifier: Programming Language :: Python :: 3
Classifier: License :: OSI Approved :: MIT License
Classifier: Operating System :: OS Independent
License-File: LICENCE.TXT
